[
{"tankid": 0, "countryid": 3, "type": 2, "tier": 8, "premium": 1, "title": "Type 59", "icon": "ch01_type59"},
{"tankid": 1, "countryid": 3, "type": 1, "tier": 7, "premium": 1, "title": "Type 62", "icon": "ch02_type62"},
{"tankid": 2, "countryid": 3, "type": 2, "tier": 8, "premium": 1, "title": "Type 59 G", "icon": "ch01_type59_gold"},
{"tankid": 3, "countryid": 3, "type": 3, "tier": 8, "premium": 1, "title": "WZ-111", "icon": "ch03_wz_111"},
{"tankid": 4, "countryid": 3, "type": 2, "tier": 7, "premium": 0, "title": "T-34-1", "icon": "ch04_t34_1"},
{"tankid": 5, "countryid": 3, "type": 1, "tier": 1, "premium": 0, "title": "Renault NC-31", "title_short": "NC-31", "icon": "ch06_renault_nc31"},
{"tankid": 6, "countryid": 3, "type": 2, "tier": 8, "premium": 0, "title": "T-34-2", "icon": "ch05_t34_2"},
{"tankid": 7, "countryid": 3, "type": 2, "tier": 9, "premium": 0, "title": "WZ-120", "icon": "ch18_wz_120"},
{"tankid": 8, "countryid": 3, "type": 3, "tier": 9, "premium": 0, "title": "WZ-111 model 1-4", "title_short": "WZ-111 1-4", "icon": "ch12_111_1_2_3"},
{"tankid": 9, "countryid": 3, "type": 1, "tier": 2, "premium": 0, "title": "Vickers Mk. E Type B", "title_short": "VAE Type B", "icon": "ch07_vickers_mke_type_bt26"},
{"tankid": 10, "countryid": 3, "type": 3, "tier": 10, "premium": 0, "title": "WZ-111 model 5A", "title_short": "WZ-111 5A", "icon": "ch13_111_4_5"},
{"tankid": 11, "countryid": 3, "type": 3, "tier": 8, "premium": 0, "title": "110", "icon": "ch11_110"},
{"tankid": 12, "countryid": 3, "type": 1, "tier": 4, "premium": 0, "title": "M5A1", "icon": "ch09_m5"},
{"tankid": 13, "countryid": 3, "type": 1, "tier": 7, "premium": 0, "title": "WZ-131", "icon": "ch16_wz_131"},
{"tankid": 14, "countryid": 3, "type": 3, "tier": 7, "premium": 0, "title": "IS-2", "icon": "ch10_is2"},
{"tankid": 15, "countryid": 3, "type": 1, "tier": 8, "premium": 0, "title": "WZ-132", "icon": "ch17_wz131_1_wz132"},
{"tankid": 16, "countryid": 3, "type": 2, "tier": 10, "premium": 0, "title": "121", "icon": "ch19_121"},
{"tankid": 17, "countryid": 3, "type": 1, "tier": 3, "premium": 0, "title": "Type 2597 Chi-Ha", "title_short": "Chi-Ha", "icon": "ch08_type97_chi_ha"},
{"tankid": 18, "countryid": 3, "type": 2, "tier": 5, "premium": 0, "title": "Type T-34", "icon": "ch21_t34"},
{"tankid": 19, "countryid": 3, "type": 1, "tier": 6, "premium": 0, "title": "59-16", "icon": "ch15_59_16"},
{"tankid": 20, "countryid": 3, "type": 2, "tier": 6, "premium": 0, "title": "Type 58", "icon": "ch20_type58"},
{"tankid": 0, "countryid": 1, "type": 2, "tier": 5, "premium": 0, "title": "PzKpfw IV", "title_short": "PzIV", "icon": "pziv"},
{"tankid": 1, "countryid": 1, "type": 5, "tier": 5, "premium": 0, "title": "Hummel", "title_short": "Hummel", "icon": "hummel"},
{"tankid": 2, "countryid": 1, "type": 3, "tier": 7, "premium": 0, "title": "PzKpfw VI Tiger", "title_short": "Tiger", "icon": "pzvi"},
{"tankid": 3, "countryid": 1, "type": 1, "tier": 2, "premium": 0, "title": "PzKpfw 35 (t)", "title_short": "Pz35t", "icon": "pz35t"},
{"tankid": 4, "countryid": 1, "type": 4, "tier": 5, "premium": 0, "title": "StuG III", "title_short": "StuGIII", "icon": "stugiii"},
{"tankid": 5, "countryid": 1, "type": 2, "tier": 7, "premium": 0, "title": "PzKpfw V Panther", "title_short": "Panther", "icon": "pzv"},
{"tankid": 6, "countryid": 1, "type": 4, "tier": 6, "premium": 0, "title": "JagdPz IV", "title_short": "JagdPzIV", "icon": "jagdpziv"},
{"tankid": 7, "countryid": 1, "type": 4, "tier": 4, "premium": 0, "title": "Hetzer", "title_short": "Hetzer", "icon": "hetzer"},
{"tankid": 8, "countryid": 1, "type": 1, "tier": 2, "premium": 0, "title": "PzKpfw II", "title_short": "PzII", "icon": "pzii"},
{"tankid": 9, "countryid": 1, "type": 2, "tier": 6, "premium": 0, "title": "VK 3601 (H)", "title_short": "VK3601H", "icon": "vk3601h"},
{"tankid": 10, "countryid": 1, "type": 2, "tier": 6, "premium": 0, "title": "VK 3001 (H)", "title_short": "VK3001H", "icon": "vk3001h"},
{"tankid": 11, "countryid": 1, "type": 5, "tier": 2, "premium": 0, "title": "Sturmpanzer I Bison", "title_short": "Bison", "icon": "bison_i"},
{"tankid": 12, "countryid": 1, "type": 1, "tier": 1, "premium": 0, "title": "Leichttraktor", "title_short": "LTraktor", "icon": "ltraktor"},
{"tankid": 13, "countryid": 1, "type": 1, "tier": 3, "premium": 0, "title": "PzKpfw 38 (t)", "title_short": "Pz38t", "icon": "pz38t"},
{"tankid": 14, "countryid": 1, "type": 4, "tier": 2, "premium": 0, "title": "Panzerjaeger I", "title_short": "PzJg I", "icon": "panzerjager_i"},
{"tankid": 15, "countryid": 1, "type": 4, "tier": 7, "premium": 0, "title": "Jagdpanther", "title_short": "JgPanther", "icon": "jagdpanther"},
{"tankid": 16, "countryid": 1, "type": 2, "tier": 7, "premium": 0, "title": "VK 3002 (DB)", "title_short": "VK3002DB", "icon": "vk3002db"},
{"tankid": 17, "countryid": 1, "type": 2, "tier": 4, "premium": 0, "title": "PzKpfw III", "title_short": "PzIII", "icon": "pziii"},
{"tankid": 18, "countryid": 1, "type": 5, "tier": 3, "premium": 0, "title": "Sturmpanzer II", "title_short": "StPz II", "icon": "sturmpanzer_ii"},
{"tankid": 19, "countryid": 1, "type": 1, "tier": 3, "premium": 0, "title": "PzKpfw III Ausf. A", "title_short": "PzIII A", "icon": "pziii_a"},
{"tankid": 20, "countryid": 1, "type": 3, "tier": 8, "premium": 0, "title": "PzKpfw VIB Tiger II", "title_short": "Tiger II", "icon": "pzvib_tiger_ii"},
{"tankid": 21, "countryid": 1, "type": 1, "tier": 4, "premium": 0, "title": "VK 1602 Leopard", "title_short": "Leopard", "icon": "vk1602"},
{"tankid": 22, "countryid": 1, "type": 5, "tier": 4, "premium": 0, "title": "Grille", "title_short": "Grille", "icon": "grille"},
{"tankid": 23, "countryid": 1, "type": 5, "tier": 3, "premium": 0, "title": "Wespe", "title_short": "Wespe", "icon": "wespe"},
{"tankid": 24, "countryid": 1, "type": 1, "tier": 3, "premium": 0, "title": "PzKpfw II Luchs", "title_short": "Luchs", "icon": "pzii_luchs"},
{"tankid": 25, "countryid": 1, "type": 2, "tier": 5, "premium": 0, "title": "PzKpfw III/IV", "title_short": "PzIII/IV", "icon": "pziii_iv"},
{"tankid": 26, "countryid": 1, "type": 4, "tier": 3, "premium": 0, "title": "Marder II", "title_short": "Marder II", "icon": "g20_marder_ii"},
{"tankid": 27, "countryid": 1, "type": 3, "tier": 10, "premium": 0, "title": "Maus", "title_short": "Maus", "icon": "maus"},
{"tankid": 28, "countryid": 1, "type": 2, "tier": 6, "premium": 0, "title": "VK 3001 (P)", "title_short": "VK3001P", "icon": "vk3001p"},
{"tankid": 29, "countryid": 1, "type": 3, "tier": 9, "premium": 0, "title": "VK 4502 (P) Ausf. B", "title_short": "VK4502P", "icon": "vk4502p"},
{"tankid": 30, "countryid": 1, "type": 4, "tier": 8, "premium": 0, "title": "Ferdinand", "icon": "ferdinand"},
{"tankid": 31, "countryid": 1, "type": 4, "tier": 9, "premium": 0, "title": "Jagdtiger", "icon": "jagdtiger"},
{"tankid": 32, "countryid": 1, "type": 1, "tier": 4, "premium": 0, "title": "PzKpfw 38 nA", "title_short": "Pz38nA", "icon": "pz38_na"},
{"tankid": 33, "countryid": 1, "type": 2, "tier": 8, "premium": 0, "title": "Panther II", "title_short": "Panther II", "icon": "panther_ii"},
{"tankid": 34, "countryid": 1, "type": 5, "tier": 7, "premium": 0, "title": "GW Tiger", "title_short": "GwTiger", "icon": "g_tiger"},
{"tankid": 35, "countryid": 1, "type": 5, "tier": 6, "premium": 0, "title": "GW Panther", "title_short": "GwPanther", "icon": "g_panther"},
{"tankid": 36, "countryid": 1, "type": 5, "tier": 8, "premium": 0, "title": "GW Typ E", "title_short": "GwTyp E", "icon": "g_e"},
{"tankid": 37, "countryid": 1, "type": 3, "tier": 10, "premium": 0, "title": "E-100", "title_short": "E-100", "icon": "e_100"},
{"tankid": 38, "countryid": 1, "type": 3, "tier": 9, "premium": 0, "title": "E-75", "title_short": "E-75", "icon": "e_75"},
{"tankid": 39, "countryid": 1, "type": 1, "tier": 5, "premium": 0, "title": "VK 2801", "title_short": "VK2801", "icon": "vk2801"},
{"tankid": 40, "countryid": 1, "type": 2, "tier": 9, "premium": 0, "title": "E-50", "title_short": "E-50", "icon": "e_50"},
{"tankid": 41, "countryid": 1, "type": 3, "tier": 8, "premium": 0, "title": "VK 4502 (P) Ausf. A", "title_short": "VK4502A", "icon": "vk4502a"},
{"tankid": 42, "countryid": 1, "type": 3, "tier": 7, "premium": 0, "title": "PzKpfw VI Tiger (P)", "title_short": "Tiger P", "icon": "pzvi_tiger_p"},
{"tankid": 45, "countryid": 1, "type": 4, "tier": 8, "premium": 0, "title": "Jagdpanther II", "title_short": "JgPanthII", "icon": "jagdpantherii"},
{"tankid": 47, "countryid": 1, "type": 4, "tier": 10, "premium": 0, "title": "JagdPz E-100", "title_short": "JgPzE100", "icon": "jagdpz_e100"},
{"tankid": 48, "countryid": 1, "type": 2, "tier": 10, "premium": 0, "title": "E-50 Ausf. M", "title_short": "E-50M", "icon": "e50_ausf_m"},
{"tankid": 201, "countryid": 1, "type": 2, "tier": 6, "premium": 1, "title": "PzKpfw V-IV", "title_short": "PzV/IV", "icon": "pzv_pziv"},
{"tankid": 202, "countryid": 1, "type": 1, "tier": 3, "premium": 1, "title": "PzKpfw II Ausf. J", "title_short": "PzII J", "icon": "pzii_j"},
{"tankid": 203, "countryid": 1, "type": 2, "tier": 3, "premium": 1, "title": "PzKpfw S35 739 (f)", "title_short": "Pz S35", "icon": "s35_captured"},
{"tankid": 204, "countryid": 1, "type": 3, "tier": 4, "premium": 1, "title": "PzKpfw B2 740 (f)", "title_short": "Pz B2", "icon": "b_1bis_captured"},
{"tankid": 205, "countryid": 1, "type": 1, "tier": 2, "premium": 1, "title": "PzKpfw 38H735 (f)", "title_short": "Pz38H735f", "icon": "h39_captured"},
{"tankid": 211, "countryid": 1, "type": 2, "tier": 6, "premium": 1, "title": "PzKpfw V-IV Alpha", "title_short": "PzV/IV A", "icon": "pzv_pziv_ausf_alfa"},
{"tankid": 212, "countryid": 1, "type": 3, "tier": 8, "premium": 1, "title": "Loewe", "icon": "lowe"},
{"tankid": 213, "countryid": 1, "type": 2, "tier": 5, "premium": 1, "title": "T-25", "title_short": "T-25", "icon": "t_25"},
{"tankid": 214, "countryid": 1, "type": 1, "tier": 3, "premium": 1, "title": "T-15", "title_short": "T-15", "icon": "t_15"},
{"tankid": 215, "countryid": 1, "type": 2, "tier": 5, "premium": 1, "title": "PzKpfw IV Hydraulic", "title_short": "PzIV Hyd.", "icon": "pziv_hydro"},
{"tankid": 216, "countryid": 1, "type": 4, "tier": 8, "premium": 1, "title": "8.8 cm PaK 43 Jagdtiger", "title_short": "JgTig.8.8 cm", "icon": "jagdtiger_sdkfz_185"},
{"tankid": 223, "countryid": 1, "type": 4, "tier": 6, "premium": 1, "title": "Dicker Max", "title_short": "D. Max", "icon": "dickermax"},
{"tankid": 224, "countryid": 1, "type": 2, "tier": 6, "premium": 1, "title": "PzKpfw IV Schmalturm", "title_short": "PzIV S.", "icon": "pziv_schmalturm"},
{"tankid": 225, "countryid": 1, "type": 2, "tier": 7, "premium": 1, "title": "Panther-M10", "title_short": "PzV/M10", "icon": "panther_m10"},
{"tankid": 1, "countryid": 4, "type": 2, "tier": 3, "premium": 0, "title": "D2", "title_short": "D2", "icon": "d2"},
{"tankid": 2, "countryid": 4, "type": 1, "tier": 1, "premium": 0, "title": "RenaultFT", "title_short": "FT-17", "icon": "renaultft"},
{"tankid": 3, "countryid": 4, "type": 5, "tier": 2, "premium": 0, "title": "RenaultBS", "title_short": "BS", "icon": "renaultbs"},
{"tankid": 4, "countryid": 4, "type": 3, "tier": 4, "premium": 0, "title": "B1", "title_short": "B1", "icon": "b1"},
{"tankid": 5, "countryid": 4, "type": 1, "tier": 2, "premium": 0, "title": "Hotchkiss H35", "title_short": "H35", "icon": "hotchkiss_h35"},
{"tankid": 6, "countryid": 4, "type": 1, "tier": 2, "premium": 0, "title": "D1", "title_short": "D1", "icon": "d1"},
{"tankid": 8, "countryid": 4, "type": 5, "tier": 4, "premium": 1, "title": "105 leFH18B2", "title_short": "leFH18B2", "icon": "_105_lefh18b2"},
{"tankid": 9, "countryid": 4, "type": 4, "tier": 3, "premium": 1, "title": "FCM36 PaK40", "title_short": "FCM36P40", "icon": "fcm_36pak40"},
{"tankid": 10, "countryid": 4, "type": 3, "tier": 6, "premium": 0, "title": "ARL 44", "title_short": "ARL 44", "icon": "arl_44"},
{"tankid": 11, "countryid": 4, "type": 1, "tier": 4, "premium": 0, "title": "AMX 40", "title_short": "AMX 40", "icon": "amx40"},
{"tankid": 12, "countryid": 4, "type": 3, "tier": 8, "premium": 0, "title": "AMX 50 100", "title_short": "AMX50 100", "icon": "amx_50_100"},
{"tankid": 13, "countryid": 4, "type": 5, "tier": 3, "premium": 0, "title": "Lorraine39 L AM", "title_short": "Lorr.39LAM", "icon": "lorraine39_l_am"},
{"tankid": 14, "countryid": 4, "type": 2, "tier": 10, "premium": 0, "title": "Bat Chatillon 25 t", "title_short": "BatChat.25t", "icon": "bat_chatillon25t"},
{"tankid": 15, "countryid": 4, "type": 3, "tier": 9, "premium": 0, "title": "AMX 50 120", "title_short": "AMX50 120", "icon": "amx_50_120"},
{"tankid": 16, "countryid": 4, "type": 5, "tier": 4, "premium": 0, "title": "AMX 105AM", "title_short": "AMX105AM", "icon": "amx_105am"},
{"tankid": 18, "countryid": 4, "type": 5, "tier": 5, "premium": 0, "title": "AMX 13 F3 AM", "title_short": "AMX-13F3", "icon": "amx_13f3am"},
{"tankid": 19, "countryid": 4, "type": 1, "tier": 8, "premium": 0, "title": "AMX 13 90", "title_short": "AMX 13 90", "icon": "amx_13_90"},
{"tankid": 20, "countryid": 4, "type": 1, "tier": 7, "premium": 0, "title": "AMX 13 75", "title_short": "AMX 13 75", "icon": "amx_13_75"},
{"tankid": 22, "countryid": 4, "type": 2, "tier": 9, "premium": 0, "title": "Lorraine 40 t", "title_short": "Lorraine40t", "icon": "lorraine40t"},
{"tankid": 23, "countryid": 4, "type": 1, "tier": 3, "premium": 0, "title": "AMX 38", "title_short": "AMX 38", "icon": "amx38"},
{"tankid": 24, "countryid": 4, "type": 3, "tier": 10, "premium": 0, "title": "AMX 50B", "title_short": "AMX50B", "icon": "f10_amx_50b"},
{"tankid": 25, "countryid": 4, "type": 1, "tier": 6, "premium": 0, "title": "AMX 12t", "title_short": "AMX12t", "icon": "amx_12t"},
{"tankid": 26, "countryid": 4, "type": 3, "tier": 5, "premium": 0, "title": "BDR G1B", "title_short": "BDR G1B", "icon": "bdr_g1b"},
{"tankid": 27, "countryid": 4, "type": 3, "tier": 7, "premium": 0, "title": "AMX M4(1945)", "title_short": "AMX M4 45", "icon": "amx_m4_1945"},
{"tankid": 28, "countryid": 4, "type": 5, "tier": 6, "premium": 0, "title": "Lorraine155 50", "title_short": "Lor.155 50", "icon": "lorraine155_50"},
{"tankid": 29, "countryid": 4, "type": 5, "tier": 7, "premium": 0, "title": "Lorraine155 51", "title_short": "Lor.155 51", "icon": "lorraine155_51"},
{"tankid": 30, "countryid": 4, "type": 4, "tier": 2, "premium": 0, "title": "RenaultFT AC", "title_short": "Ren.FT AC", "icon": "renaultft_ac"},
{"tankid": 32, "countryid": 4, "type": 4, "tier": 3, "premium": 0, "title": "Renault UE 57", "title_short": "Ren.UE57", "icon": "renaultue57"},
{"tankid": 38, "countryid": 4, "type": 4, "tier": 4, "premium": 0, "title": "Somua SAu-40", "title_short": "SAu-40", "icon": "somua_sau_40"},
{"tankid": 39, "countryid": 4, "type": 4, "tier": 5, "premium": 0, "title": "S-35 CA", "title_short": "S-35CA", "icon": "s_35ca"},
{"tankid": 42, "countryid": 4, "type": 4, "tier": 7, "premium": 0, "title": "AMX AC Mle. 1946", "title_short": "AC Mle.46", "icon": "amx_ac_mle1946"},
{"tankid": 43, "countryid": 4, "type": 4, "tier": 9, "premium": 0, "title": "AMX 50 Foch", "title_short": "AMX50Foch", "icon": "amx50_foch"},
{"tankid": 45, "countryid": 4, "type": 4, "tier": 6, "premium": 0, "title": "ARL V39", "title_short": "ARL V39", "icon": "arl_v39"},
{"tankid": 46, "countryid": 4, "type": 5, "tier": 8, "premium": 0, "title": "Bat Chatillon 155", "title_short": "B.Chat.155", "icon": "bat_chatillon155"},
{"tankid": 47, "countryid": 4, "type": 4, "tier": 8, "premium": 0, "title": "AMX AC Mle. 1948", "title_short": "AC Mle.48", "icon": "amx_ac_mle1948"},
{"tankid": 54, "countryid": 4, "type": 4, "tier": 10, "premium": 0, "title": "AMX-50 Foch (155)", "title_short": "AMX50F155", "icon": "amx_50fosh_155"},
{"tankid": 55, "countryid": 4, "type": 1, "tier": 5, "premium": 0, "title": "ELC AMX", "title_short": "ELC AMX", "icon": "elc_amx"},
{"tankid": 250, "countryid": 4, "type": 3, "tier": 8, "premium": 1, "title": "FCM 50 t", "icon": "fcm_50t"},
{"tankid": 255, "countryid": 0, "type": 1, "tier": 1, "premium": 0, "title": "Observer", "icon": "observer"},
{"tankid": 0, "countryid": 0, "type": 2, "tier": 5, "premium": 0, "title": "T-34", "icon": "t_34"},
{"tankid": 1, "countryid": 0, "type": 4, "tier": 5, "premium": 0, "title": "SU-85", "icon": "su_85"},
{"tankid": 2, "countryid": 0, "type": 3, "tier": 7, "premium": 0, "title": "IS", "icon": "is"},
{"tankid": 3, "countryid": 0, "type": 1, "tier": 3, "premium": 0, "title": "BT-7", "icon": "bt_7"},
{"tankid": 4, "countryid": 0, "type": 1, "tier": 2, "premium": 0, "title": "BT-2", "icon": "bt_2"},
{"tankid": 5, "countryid": 0, "type": 3, "tier": 5, "premium": 0, "title": "KV", "icon": "kv"},
{"tankid": 6, "countryid": 0, "type": 2, "tier": 4, "premium": 0, "title": "T-28", "icon": "t_28"},
{"tankid": 7, "countryid": 0, "type": 5, "tier": 6, "premium": 0, "title": "S-51", "icon": "s_51"},
{"tankid": 8, "countryid": 0, "type": 1, "tier": 4, "premium": 0, "title": "A-20", "icon": "a_20"},
{"tankid": 9, "countryid": 0, "type": 4, "tier": 7, "premium": 0, "title": "SU-152", "icon": "su_152"},
{"tankid": 10, "countryid": 0, "type": 2, "tier": 6, "premium": 0, "title": "T-34-85", "icon": "t_34_85"},
{"tankid": 11, "countryid": 0, "type": 3, "tier": 6, "premium": 0, "title": "KV-1S", "icon": "kv_1s"},
{"tankid": 12, "countryid": 0, "type": 1, "tier": 3, "premium": 0, "title": "T-46", "icon": "t_46"},
{"tankid": 13, "countryid": 0, "type": 1, "tier": 1, "premium": 0, "title": "MS-1", "icon": "ms_1"},
{"tankid": 14, "countryid": 0, "type": 4, "tier": 6, "premium": 0, "title": "SU-100", "icon": "su_100"},
{"tankid": 15, "countryid": 0, "type": 5, "tier": 2, "premium": 0, "title": "SU-18", "icon": "su_18"},
{"tankid": 16, "countryid": 0, "type": 5, "tier": 6, "premium": 0, "title": "SU-14", "icon": "su_14"},
{"tankid": 17, "countryid": 0, "type": 2, "tier": 8, "premium": 0, "title": "T-44", "icon": "t_44"},
{"tankid": 18, "countryid": 0, "type": 1, "tier": 2, "premium": 0, "title": "T-26", "icon": "t_26"},
{"tankid": 19, "countryid": 0, "type": 5, "tier": 4, "premium": 0, "title": "SU-5", "icon": "su_5"},
{"tankid": 20, "countryid": 0, "type": 4, "tier": 2, "premium": 0, "title": "AT-1", "icon": "at_1"},
{"tankid": 21, "countryid": 0, "type": 3, "tier": 8, "premium": 0, "title": "IS-3", "icon": "is_3"},
{"tankid": 22, "countryid": 0, "type": 5, "tier": 5, "premium": 0, "title": "SU-8", "icon": "su_8"},
{"tankid": 23, "countryid": 0, "type": 3, "tier": 7, "premium": 0, "title": "KV-3", "icon": "kv_3"},
{"tankid": 24, "countryid": 0, "type": 3, "tier": 10, "premium": 0, "title": "IS-4", "icon": "is_4"},
{"tankid": 25, "countryid": 0, "type": 4, "tier": 3, "premium": 0, "title": "SU-76", "icon": "su_76"},
{"tankid": 26, "countryid": 0, "type": 2, "tier": 7, "premium": 0, "title": "T-43", "icon": "t_43"},
{"tankid": 27, "countryid": 0, "type": 4, "tier": 4, "premium": 0, "title": "SU-85B", "icon": "gaz_74b"},
{"tankid": 28, "countryid": 0, "type": 3, "tier": 10, "premium": 0, "title": "IS-7", "icon": "is_7"},
{"tankid": 29, "countryid": 0, "type": 4, "tier": 8, "premium": 0, "title": "ISU-152", "icon": "isu_152"},
{"tankid": 30, "countryid": 0, "type": 5, "tier": 3, "premium": 0, "title": "SU-26", "icon": "su_26"},
{"tankid": 31, "countryid": 0, "type": 2, "tier": 9, "premium": 0, "title": "T-54", "icon": "t_54"},
{"tankid": 32, "countryid": 0, "type": 4, "tier": 9, "premium": 0, "title": "Object 704", "title_short": "Obj. 704", "icon": "object_704"},
{"tankid": 33, "countryid": 0, "type": 5, "tier": 7, "premium": 0, "title": "Object 212", "title_short": "Obj. 212", "icon": "object_212"},
{"tankid": 34, "countryid": 0, "type": 5, "tier": 8, "premium": 0, "title": "Object 261", "title_short": "Obj. 261", "icon": "object_261"},
{"tankid": 35, "countryid": 0, "type": 2, "tier": 7, "premium": 0, "title": "KV-13", "icon": "kv_13"},
{"tankid": 36, "countryid": 0, "type": 3, "tier": 8, "premium": 1, "title": "IS-6", "icon": "object252"},
{"tankid": 37, "countryid": 0, "type": 1, "tier": 4, "premium": 0, "title": "T-50", "title_short": "T-50", "icon": "t_50"},
{"tankid": 38, "countryid": 0, "type": 1, "tier": 5, "premium": 0, "title": "T-50-2", "title_short": "T-50-2", "icon": "t_50_2"},
{"tankid": 39, "countryid": 0, "type": 4, "tier": 8, "premium": 0, "title": "SU-101", "title_short": "SU-101", "icon": "su_101"},
{"tankid": 40, "countryid": 0, "type": 4, "tier": 7, "premium": 0, "title": "SU-100M1", "icon": "su100m1"},
{"tankid": 41, "countryid": 0, "type": 3, "tier": 6, "premium": 0, "title": "KV-2", "icon": "kv2"},
{"tankid": 42, "countryid": 0, "type": 3, "tier": 9, "premium": 0, "title": "ST-I", "icon": "st_i"},
{"tankid": 43, "countryid": 0, "type": 3, "tier": 8, "premium": 0, "title": "KV-4", "icon": "kv4"},
{"tankid": 44, "countryid": 0, "type": 3, "tier": 6, "premium": 0, "title": "T-150", "icon": "t150"},
{"tankid": 45, "countryid": 0, "type": 3, "tier": 9, "premium": 0, "title": "IS-8", "icon": "is8"},
{"tankid": 46, "countryid": 0, "type": 3, "tier": 5, "premium": 0, "title": "KV-1", "icon": "kv1"},
{"tankid": 47, "countryid": 0, "type": 4, "tier": 9, "premium": 0, "title": "SU-122-54", "title_short": "SU-122-54", "icon": "su122_54"},
{"tankid": 53, "countryid": 0, "type": 4, "tier": 10, "premium": 0, "title": "Object 268", "title_short": "Obj. 268", "icon": "object268"},
{"tankid": 54, "countryid": 0, "type": 2, "tier": 10, "premium": 0, "title": "T-62A", "icon": "t62a"},
{"tankid": 56, "countryid": 0, "type": 4, "tier": 10, "premium": 0, "title": "Object 263", "title_short": "Obj. 263", "icon": "object263"},
{"tankid": 200, "countryid": 0, "type": 3, "tier": 5, "premium": 1, "title": "KV-220 Beta-Test", "title_short": "KV-220 T", "icon": "kv_220"},
{"tankid": 201, "countryid": 0, "type": 2, "tier": 5, "premium": 1, "title": "Matilda IV", "icon": "matilda_ii_ll"},
{"tankid": 202, "countryid": 0, "type": 3, "tier": 5, "premium": 1, "title": "Churchill III", "icon": "churchill_ll"},
{"tankid": 204, "countryid": 0, "type": 1, "tier": 3, "premium": 1, "title": "BT-SV", "icon": "bt_sv"},
{"tankid": 205, "countryid": 0, "type": 1, "tier": 4, "premium": 1, "title": "Valentine II", "icon": "valentine_ll"},
{"tankid": 206, "countryid": 0, "type": 1, "tier": 3, "premium": 1, "title": "M3 Stuart LL", "icon": "m3_stuart_ll"},
{"tankid": 207, "countryid": 0, "type": 2, "tier": 4, "premium": 1, "title": "A-32", "icon": "a_32"},
{"tankid": 208, "countryid": 0, "type": 3, "tier": 8, "premium": 1, "title": "KV-5", "icon": "kv_5"},
{"tankid": 209, "countryid": 0, "type": 1, "tier": 3, "premium": 1, "title": "T-127", "icon": "t_127"},
{"tankid": 210, "countryid": 0, "type": 4, "tier": 5, "premium": 1, "title": "SU-85I", "icon": "su_85i"},
{"tankid": 211, "countryid": 0, "type": 3, "tier": 5, "premium": 1, "title": "KV-220", "icon": "kv_220_action"},
{"tankid": 213, "countryid": 0, "type": 1, "tier": 2, "premium": 1, "title": "Tetrarch", "title_short": "Tetrarch", "icon": "tetrarch_ll"},
{"tankid": 214, "countryid": 0, "type": 4, "tier": 6, "premium": 1, "title": "SU-100Y", "icon": "su100y"},
{"tankid": 216, "countryid": 0, "type": 4, "tier": 7, "premium": 1, "title": "SU-122-44", "icon": "su122_44"},
{"tankid": 0, "countryid": 2, "type": 3, "tier": 5, "premium": 1, "title": "T14", "icon": "t14"},
{"tankid": 1, "countryid": 2, "type": 1, "tier": 3, "premium": 0, "title": "M3 Stuart", "icon": "m3_stuart"},
{"tankid": 2, "countryid": 2, "type": 1, "tier": 1, "premium": 0, "title": "T1 Cunningham", "title_short": "T1", "icon": "t1_cunningham"},
{"tankid": 3, "countryid": 2, "type": 3, "tier": 6, "premium": 0, "title": "M6", "icon": "m6"},
{"tankid": 4, "countryid": 2, "type": 2, "tier": 5, "premium": 0, "title": "M4 Sherman", "title_short": "M4", "icon": "m4_sherman"},
{"tankid": 5, "countryid": 2, "type": 2, "tier": 6, "premium": 0, "title": "M4A3E8 Sherman", "title_short": "M4A3E8", "icon": "m4a3e8_sherman"},
{"tankid": 6, "countryid": 2, "type": 2, "tier": 7, "premium": 0, "title": "T20", "icon": "t20"},
{"tankid": 7, "countryid": 2, "type": 1, "tier": 2, "premium": 0, "title": "M2 Light Tank", "title_short": "M2 Light", "icon": "m2_lt"},
{"tankid": 8, "countryid": 2, "type": 5, "tier": 2, "premium": 0, "title": "T57", "icon": "t57"},
{"tankid": 9, "countryid": 2, "type": 2, "tier": 8, "premium": 0, "title": "T23", "icon": "t23"},
{"tankid": 10, "countryid": 2, "type": 4, "tier": 9, "premium": 0, "title": "T30", "icon": "t30"},
{"tankid": 11, "countryid": 2, "type": 3, "tier": 8, "premium": 1, "title": "T34", "icon": "t34_hvy"},
{"tankid": 12, "countryid": 2, "type": 2, "tier": 4, "premium": 0, "title": "M3 Lee", "icon": "m3_grant"},
{"tankid": 13, "countryid": 2, "type": 3, "tier": 5, "premium": 0, "title": "T1 Heavy Tank", "title_short": "T1 Heavy", "icon": "t1_hvy"},
{"tankid": 14, "countryid": 2, "type": 5, "tier": 4, "premium": 0, "title": "M7 Priest", "icon": "m7_priest"},
{"tankid": 15, "countryid": 2, "type": 3, "tier": 7, "premium": 0, "title": "T29", "icon": "t29"},
{"tankid": 16, "countryid": 2, "type": 5, "tier": 5, "premium": 0, "title": "M41", "icon": "m41"},
{"tankid": 17, "countryid": 2, "type": 3, "tier": 8, "premium": 0, "title": "T32", "icon": "t32"},
{"tankid": 18, "countryid": 2, "type": 5, "tier": 3, "premium": 0, "title": "M37", "icon": "m37"},
{"tankid": 19, "countryid": 2, "type": 2, "tier": 3, "premium": 0, "title": "M2 Medium Tank", "title_short": "M2 Medium", "icon": "m2_med"},
{"tankid": 20, "countryid": 2, "type": 1, "tier": 4, "premium": 0, "title": "M5 Stuart", "title_short": "M5 Stuart", "icon": "m5_stuart"},
{"tankid": 21, "countryid": 2, "type": 2, "tier": 5, "premium": 0, "title": "M7", "title_short": "M7", "icon": "m7_med"},
{"tankid": 22, "countryid": 2, "type": 2, "tier": 2, "premium": 0, "title": "T2 Medium Tank", "title_short": "T2 Medium", "icon": "t2_med"},
{"tankid": 23, "countryid": 2, "type": 2, "tier": 8, "premium": 0, "title": "M26 Pershing", "title_short": "Pershing", "icon": "pershing"},
{"tankid": 24, "countryid": 2, "type": 4, "tier": 2, "premium": 0, "title": "T18", "icon": "t18"},
{"tankid": 25, "countryid": 2, "type": 4, "tier": 3, "premium": 0, "title": "T82", "icon": "t82"},
{"tankid": 27, "countryid": 2, "type": 4, "tier": 5, "premium": 0, "title": "M10 Wolverine", "title_short": "Wolverine", "icon": "m10_wolverine"},
{"tankid": 28, "countryid": 2, "type": 4, "tier": 6, "premium": 0, "title": "M36 Jackson", "title_short": "Jackson", "icon": "m36_slagger"},
{"tankid": 29, "countryid": 2, "type": 5, "tier": 7, "premium": 0, "title": "M40/M43", "icon": "m40m43"},
{"tankid": 30, "countryid": 2, "type": 4, "tier": 4, "premium": 0, "title": "T40", "icon": "t40"},
{"tankid": 31, "countryid": 2, "type": 5, "tier": 6, "premium": 0, "title": "M12", "icon": "m12"},
{"tankid": 32, "countryid": 2, "type": 4, "tier": 8, "premium": 0, "title": "T28", "title_short": "T28", "icon": "t28"},
{"tankid": 33, "countryid": 2, "type": 5, "tier": 8, "premium": 0, "title": "T92", "icon": "t92"},
{"tankid": 34, "countryid": 2, "type": 4, "tier": 9, "premium": 0, "title": "T95", "icon": "t95"},
{"tankid": 35, "countryid": 2, "type": 2, "tier": 9, "premium": 0, "title": "M46 Patton", "title_short": "M46 Patton", "icon": "m46_patton"},
{"tankid": 36, "countryid": 2, "type": 4, "tier": 7, "premium": 0, "title": "T25 AT", "title_short": "T25 AT", "icon": "t25_at"},
{"tankid": 37, "countryid": 2, "type": 3, "tier": 9, "premium": 0, "title": "M103", "icon": "m103"},
{"tankid": 38, "countryid": 2, "type": 1, "tier": 5, "premium": 0, "title": "M24 Chaffee", "title_short": "Chaffee", "icon": "m24_chaffee"},
{"tankid": 39, "countryid": 2, "type": 2, "tier": 6, "premium": 0, "title": "M4A3E2 Sherman Jumbo", "title_short": "M4A3E2", "icon": "sherman_jumbo"},
{"tankid": 40, "countryid": 2, "type": 4, "tier": 4, "premium": 0, "title": "M8A1", "icon": "m8a1"},
{"tankid": 41, "countryid": 2, "type": 4, "tier": 5, "premium": 0, "title": "T49", "icon": "t49"},
{"tankid": 42, "countryid": 2, "type": 3, "tier": 10, "premium": 0, "title": "T110E5", "icon": "t110"},
{"tankid": 43, "countryid": 2, "type": 4, "tier": 7, "premium": 0, "title": "T25/2", "title_short": "T25/2", "icon": "t25_2"},
{"tankid": 44, "countryid": 2, "type": 4, "tier": 8, "premium": 0, "title": "T28 Prototype", "title_short": "T28 Prot.", "icon": "t28_prototype"},
{"tankid": 45, "countryid": 2, "type": 4, "tier": 6, "premium": 0, "title": "M18 Hellcat", "title_short": "Hellcat", "icon": "m18_hellcat"},
{"tankid": 51, "countryid": 2, "type": 4, "tier": 10, "premium": 0, "title": "T110E4", "icon": "t110e4"},
{"tankid": 52, "countryid": 2, "type": 2, "tier": 8, "premium": 1, "title": "T26E4 Super Pershing", "title_short": "T26E4", "icon": "t26_e4_superpershing"},
{"tankid": 54, "countryid": 2, "type": 4, "tier": 10, "premium": 0, "title": "T110E3", "icon": "t110e3"},
{"tankid": 55, "countryid": 2, "type": 2, "tier": 10, "premium": 0, "title": "M48A1 Patton", "title_short": "M48 Patton", "icon": "m48a1"},
{"tankid": 57, "countryid": 2, "type": 2, "tier": 8, "premium": 0, "title": "T69", "title_short": "T69", "icon": "t69"},
{"tankid": 58, "countryid": 2, "type": 3, "tier": 10, "premium": 0, "title": "T57 Heavy Tank", "title_short": "T57 Heavy", "icon": "t57_58"},
{"tankid": 59, "countryid": 2, "type": 1, "tier": 6, "premium": 0, "title": "T21", "icon": "t21"},
{"tankid": 60, "countryid": 2, "type": 2, "tier": 9, "premium": 0, "title": "T54E1", "icon": "t54e1"},
{"tankid": 61, "countryid": 2, "type": 1, "tier": 7, "premium": 0, "title": "T71", "icon": "t71"},
{"tankid": 201, "countryid": 2, "type": 1, "tier": 2, "premium": 1, "title": "T2 Light Tank", "title_short": "T2 Light", "icon": "t2_lt"},
{"tankid": 202, "countryid": 2, "type": 2, "tier": 5, "premium": 1, "title": "Ram II", "icon": "ram_ii"},
{"tankid": 203, "countryid": 2, "type": 1, "tier": 3, "premium": 1, "title": "MTLS-1G14", "icon": "mtls_1g14"},
{"tankid": 204, "countryid": 2, "type": 2, "tier": 5, "premium": 1, "title": "M4A2E4 Sherman", "title_short": "M4A2E4", "icon": "m4a2e4"},
{"tankid": 205, "countryid": 2, "type": 3, "tier": 8, "premium": 1, "title": "M6A2E1", "icon": "m6a2e1"},
{"tankid": 206, "countryid": 2, "type": 1, "tier": 3, "premium": 1, "title": "M22 Locust", "title_short": "Locust", "icon": "m22_locust"},
{"tankid": 209, "countryid": 2, "type": 1, "tier": 2, "premium": 1, "title": "T1E6", "title_short": "T1E6", "icon": "t1_e6"},
{"tankid": 0, "countryid": 5, "type": 1, "tier": 1, "premium": 0, "title": "Vickers Medium Mk. I", "title_short": "Medium I", "icon": "gb01_medium_mark_i"},
{"tankid": 1, "countryid": 5, "type": 2, "tier": 2, "premium": 0, "title": "Vickers Medium Mk. II", "title_short": "Medium II", "icon": "gb05_vickers_medium_mk_ii"},
{"tankid": 3, "countryid": 5, "type": 2, "tier": 4, "premium": 0, "title": "Matilda", "title_short": "Matilda", "icon": "gb07_matilda"},
{"tankid": 4, "countryid": 5, "type": 2, "tier": 6, "premium": 0, "title": "Cromwell", "title_short": "Cromwell", "icon": "gb21_cromwell"},
{"tankid": 8, "countryid": 5, "type": 1, "tier": 5, "premium": 0, "title": "Crusader", "title_short": "Crusader", "icon": "gb20_crusader"},
{"tankid": 9, "countryid": 5, "type": 2, "tier": 3, "premium": 0, "title": "Vickers Medium Mk. III", "title_short": "Medium III", "icon": "gb06_vickers_medium_mk_iii"},
{"tankid": 11, "countryid": 5, "type": 3, "tier": 5, "premium": 0, "title": "Churchill I", "title_short": "Churchill I", "icon": "gb08_churchill_i"},
{"tankid": 12, "countryid": 5, "type": 3, "tier": 7, "premium": 0, "title": "Black Prince", "title_short": "Black Prince", "icon": "gb10_black_prince"},
{"tankid": 15, "countryid": 5, "type": 3, "tier": 8, "premium": 0, "title": "Caernarvon", "title_short": "Caernarvon", "icon": "gb11_caernarvon"},
{"tankid": 17, "countryid": 5, "type": 3, "tier": 9, "premium": 0, "title": "Conqueror", "icon": "gb12_conqueror"},
{"tankid": 18, "countryid": 5, "type": 3, "tier": 6, "premium": 0, "title": "Churchill VII", "icon": "gb09_churchill_vii"},
{"tankid": 19, "countryid": 5, "type": 1, "tier": 4, "premium": 0, "title": "Valentine", "title_short": "Valentine", "icon": "gb04_valentine"},
{"tankid": 20, "countryid": 5, "type": 1, "tier": 2, "premium": 0, "title": "Cruiser Mk. I", "title_short": "Cruiser I", "icon": "gb03_cruiser_mk_i"},
{"tankid": 21, "countryid": 5, "type": 2, "tier": 7, "premium": 0, "title": "Comet", "title_short": "Comet", "icon": "gb22_comet"},
{"tankid": 22, "countryid": 5, "type": 2, "tier": 9, "premium": 0, "title": "Centurion Mk. 7/1", "title_short": "Centurion 7/1", "icon": "gb24_centurion_mk3"},
{"tankid": 23, "countryid": 5, "type": 2, "tier": 8, "premium": 0, "title": "Centurion Mk. I", "title_short": "Centurion I", "icon": "gb23_centurion"},
{"tankid": 24, "countryid": 5, "type": 3, "tier": 10, "premium": 0, "title": "FV215b", "icon": "gb13_fv215b"},
{"tankid": 25, "countryid": 5, "type": 1, "tier": 4, "premium": 0, "title": "Covenanter", "title_short": "Covenanter", "icon": "gb60_covenanter"},
{"tankid": 27, "countryid": 5, "type": 1, "tier": 3, "premium": 0, "title": "Cruiser Mk. II", "title_short": "Cruiser II", "icon": "gb69_cruiser_mk_ii"},
{"tankid": 28, "countryid": 5, "type": 2, "tier": 10, "premium": 0, "title": "FV4202", "title_short": "FV4202", "icon": "gb70_fv4202_105"},
{"tankid": 29, "countryid": 5, "type": 1, "tier": 3, "premium": 0, "title": "Cruiser Mk. IV", "title_short": "Cruiser IV", "icon": "gb59_cruiser_mk_iv"},
{"tankid": 30, "countryid": 5, "type": 1, "tier": 2, "premium": 0, "title": "Cruiser Mk. III", "title_short": "Cruiser III", "icon": "gb58_cruiser_mk_iii"},
{"tankid": 209, "countryid": 5, "type": 2, "tier": 5, "premium": 1, "title": "Matilda Black Prince", "title_short": "Matilda BP", "icon": "gb68_matilda_black_prince"},
{"tankid": 210, "countryid": 5, "type": 3, "tier": 6, "premium": 1, "title": "TOG II*", "icon": "gb63_tog_ii"},
{"tankid": 211, "countryid": 5, "type": 4, "tier": 7, "premium": 1, "title": "AT-15A", "icon": "gb71_at_15a"}
]
